crypto_systems_cryptosystems6300/__init__.py
crypto_systems_cryptosystems6300/token_master.py
crypto_systems_cryptosystems6300-0.0.1.dist-info/METADATA
crypto_systems_cryptosystems6300-0.0.1.dist-info/WHEEL
crypto_systems_cryptosystems6300-0.0.1.dist-info/top_level.txt
crypto_systems_cryptosystems6300-0.0.1.dist-info/RECORD
