Metadata-Version: 2.1
Name: crypto-systems-cryptosystems6300
Version: 0.0.1
Summary: To interact with crypto systems.
Requires-Python: >=3.7
